neurotorch/__init__.py
neurotorch/dimension.py
neurotorch/callbacks/__init__.py
neurotorch/callbacks/base_callback.py
neurotorch/callbacks/checkpoints_manager.py
neurotorch/callbacks/convergence.py
neurotorch/callbacks/early_stopping.py
neurotorch/callbacks/events.py
neurotorch/callbacks/history.py
neurotorch/callbacks/lr_schedulers.py
neurotorch/callbacks/training_visualization.py
neurotorch/init/__init__.py
neurotorch/learning_algorithms/__init__.py
neurotorch/learning_algorithms/bptt.py
neurotorch/learning_algorithms/eprop.py
neurotorch/learning_algorithms/learning_algorithm.py
neurotorch/learning_algorithms/rls.py
neurotorch/learning_algorithms/tbptt.py
neurotorch/metrics/__init__.py
neurotorch/metrics/base.py
neurotorch/metrics/classification.py
neurotorch/metrics/losses.py
neurotorch/metrics/regression.py
neurotorch/modules/__init__.py
neurotorch/modules/base.py
neurotorch/modules/functions.py
neurotorch/modules/sequential.py
neurotorch/modules/sequential_rnn.py
neurotorch/modules/spike_funcs.py
neurotorch/modules/utils.py
neurotorch/modules/wrappers.py
neurotorch/modules/layers/__init__.py
neurotorch/modules/layers/base.py
neurotorch/modules/layers/classical.py
neurotorch/modules/layers/leaky_integrate.py
neurotorch/modules/layers/spiking.py
neurotorch/modules/layers/spiking_lpf.py
neurotorch/modules/layers/wilson_cowan.py
neurotorch/regularization/__init__.py
neurotorch/regularization/connectome.py
neurotorch/rl/__init__.py
neurotorch/rl/agent.py
neurotorch/rl/buffers.py
neurotorch/rl/curriculum.py
neurotorch/rl/ppo.py
neurotorch/rl/rl_academy.py
neurotorch/rl/utils.py
neurotorch/trainers/__init__.py
neurotorch/trainers/classification.py
neurotorch/trainers/regression.py
neurotorch/trainers/trainer.py
neurotorch/transforms/__init__.py
neurotorch/transforms/base.py
neurotorch/transforms/spikes_auto_encoder.py
neurotorch/transforms/spikes_decoders.py
neurotorch/transforms/spikes_encoders.py
neurotorch/transforms/vision.py
neurotorch/transforms/wrappers.py
neurotorch-0.0.2.dist-info/licenses/LICENSE
neurotorch-0.0.2.dist-info/METADATA
neurotorch-0.0.2.dist-info/WHEEL
neurotorch-0.0.2.dist-info/top_level.txt
neurotorch-0.0.2.dist-info/RECORD
