Metadata-Version: 2.4
Name: NeuroTorch
Version: 0.0.2
Summary: NeuroTorch: A PyTorch-based framework for deep learning in neuroscience
Author-email: Jérémie Gince <gincejeremie@gmail.com>
Project-URL: homepage, https://neurotorch.github.io/NeuroTorch/
Project-URL: Documentation, https://neurotorch.github.io/NeuroTorch/
Project-URL: Source, https://github.com/NeuroTorch/NeuroTorch
Classifier: Development Status :: 3 - Alpha
Classifier: Intended Audience :: Science/Research
Classifier: License :: OSI Approved :: Apache Software License
Classifier: Programming Language :: Python :: 3
Classifier: Programming Language :: Python :: 3.10
Classifier: Topic :: Scientific/Engineering
Classifier: Topic :: Scientific/Engineering :: Artificial Intelligence
Classifier: Topic :: Scientific/Engineering :: Bio-Informatics
Classifier: Topic :: Software Development :: Libraries :: Python Modules
Classifier: Operating System :: OS Independent
Requires-Python: >=3.10
License-File: LICENSE
Requires-Dist: matplotlib>=3.5.2
Requires-Dist: numpy<2.0.0,>=1.22.3
Requires-Dist: setuptools>=57.0.0
Requires-Dist: torch>=1.11.0
Requires-Dist: torchvision>=0.12.0
Requires-Dist: tqdm>=4.64.0
Requires-Dist: scikit-learn>=1.1.1
Requires-Dist: psutil>=5.9.1
Requires-Dist: scipy>=1.8.0
Requires-Dist: six>=1.16.0
Requires-Dist: pythonbasictools<0.0.2,>=0.0.1a11
Requires-Dist: importlib-metadata<9.0.0,>=8.7.0
Dynamic: license-file
Dynamic: requires-python
